README.rst
setup.py
src/__init__.py
src/estimator.py
universal_divergence.egg-info/PKG-INFO
universal_divergence.egg-info/SOURCES.txt
universal_divergence.egg-info/dependency_links.txt
universal_divergence.egg-info/requires.txt
universal_divergence.egg-info/top_level.txt