Metadata-Version: 1.1
Name: universal-divergence
Version: 0.2.0
Summary: A divergence estimator of two sets of samples.
Home-page: https://github.com/slaypni/universal-divergence
Author: Kazuaki Tanida
Author-email: UNKNOWN
License: MIT
Keywords: KL,Kullback-Leibler,divergence,information measure
Platform: UNKNOWN
Classifier: Programming Language :: Python :: 2
Classifier: Programming Language :: Python :: 3
Classifier: Intended Audience :: Science/Research
Classifier: License :: OSI Approved :: MIT License
Classifier: Topic :: Scientific/Engineering
